{"google":"","body":"# CustomForms - 0.44 \r\n\r\n- Jquery pluggin to aid on styling forms in all major browsers.\r\n\r\n## Support features\r\n* Placeholders\r\n* Select element\r\n* File uploader\r\n* Checkbox\r\n* Radio\r\n\r\n## Browser support\r\n* Internet Explorer 6+\r\n* Firefox 3.5+\r\n* Google Chrome 5+\r\n* Safari 4+\r\n\r\n## Requirements\r\njQuery 1.6+\r\n\r\n## Defaults\r\n```javascript\r\n{\r\n    customEle      : 'a',\r\n    containerEle   : 'div',\r\n    classPrefix    : 'custom-',\r\n    autoHide       : 1, // Auto hide the stylized elements\r\n    active         : 0, // Load all custom form modules\r\n    select: {\r\n        active: 1\r\n    },\r\n    radio: {\r\n        active: 1\r\n    },\r\n    checkbox: {\r\n        active: 1\r\n    },\r\n    file: {\r\n        active: 1,\r\n        holderTxt: \"Upload..\"\r\n    },\r\n    text: {\r\n        active: 1,\r\n        blur_color: \"#777\"\r\n    }\r\n}\r\n```\r\n\r\n## Usage\r\n```javascript\r\n\r\n  // You can overwrite defaults by passing an object with some options\r\n  var options = { customEle: 'span' };\r\n\r\n  // All Form elements\r\n  $('form').cstmForm( options ) \r\n\r\n  // target a certain group of element \r\n  $('input[type=file]').cstmForm( options )\r\n \r\n  // You can target specific groups of elements\r\n  $('input[type=radio], input[type=checkbox], select').cstmForm( options )\r\n```\r\n","note":"Don't delete this file! It's used internally to help with page regeneration.","tagline":"CustomForms - Javascript Library to aid on creation of beautiful form elements :)","name":"Customforms"}